npc_sync/__init__.py
npc_sync/py.typed
npc_sync/sync.py
npc_sync-0.1.26.dist-info/licenses/LICENSE
npc_sync-0.1.26.dist-info/METADATA
npc_sync-0.1.26.dist-info/WHEEL
npc_sync-0.1.26.dist-info/entry_points.txt
npc_sync-0.1.26.dist-info/top_level.txt
npc_sync-0.1.26.dist-info/RECORD
