Metadata-Version: 2.4
Name: npc-sync
Version: 0.1.26
Summary: Repackaging of AllenSDK.SyncDataset with extra functionality, compatible with data in the cloud.
Author-email: Ben Hardcastle <ben.hardcastle@alleninstitue.org>
License: MIT
Project-URL: Repository, https://github.com/AllenInstitute/npc_sync
Project-URL: Issues, https://github.com/AllenInstitute/npc_sync/issues
Classifier: Development Status :: 3 - Alpha
Classifier: Programming Language :: Python :: 3
Classifier: Programming Language :: Python :: 3.9
Classifier: Programming Language :: Python :: 3.10
Classifier: Programming Language :: Python :: 3.11
Classifier: License :: OSI Approved :: MIT License
Classifier: Operating System :: Microsoft :: Windows
Classifier: Operating System :: POSIX :: Linux
Requires-Python: >=3.9
License-File: LICENSE
Requires-Dist: h5py>=3.10.0
Requires-Dist: numpy>=1.26.3
Requires-Dist: matplotlib>=3.8.2
Requires-Dist: typing-extensions>=4.9.0
Requires-Dist: npc-io>=0.1.26
Requires-Dist: npc-session>=0.1.33
Requires-Dist: scipy>=1.13.1
Requires-Dist: npc-stim>=0.1.14
Dynamic: license-file
